spotifysearch/__init__.py
spotifysearch/calls.py
spotifysearch/classes.py
spotifysearch/client.py
spotifysearch/constructor.py
spotifysearch/urlbuilder.py
spotifysearch-0.0.5.dist-info/LICENSE
spotifysearch-0.0.5.dist-info/METADATA
spotifysearch-0.0.5.dist-info/WHEEL
spotifysearch-0.0.5.dist-info/top_level.txt
spotifysearch-0.0.5.dist-info/RECORD
