Metadata-Version: 2.1
Name: spotifysearch
Version: 0.0.5
Summary: A complete wrapper for the Search API provided by Spotify written in Python.
Home-page: https://github.com/matcsantos/SpotifySearch
Author: Matheus Carvalho
License: UNKNOWN
Project-URL: Bug Tracker, https://github.com/matcsantos/SpotifySearch/issues
Platform: UNKNOWN
Classifier: Programming Language :: Python :: 3
Classifier: License :: OSI Approved :: MIT License
Classifier: Operating System :: OS Independent
Requires-Python: >=3.6
License-File: LICENSE
